wikiscraper/__init__.py
wikiscraper/scraper.py
wikiscraper_py-0.0.3.dist-info/licenses/License
wikiscraper_py-0.0.3.dist-info/METADATA
wikiscraper_py-0.0.3.dist-info/WHEEL
wikiscraper_py-0.0.3.dist-info/top_level.txt
wikiscraper_py-0.0.3.dist-info/RECORD
