Metadata-Version: 2.4
Name: wikiscraper-py
Version: 0.0.3
Summary: A Python library to scrape Wikipedia articles easily
Home-page: https://github.com/BekiChemeda/Wikiscraper
Author: Beki Chemeda
Author-email: Beki Chemeda <Bekichemeda@gmail.com>
License-Expression: MIT
Project-URL: Homepage, https://github.com/Bekichemeda/Wikiscraper
Project-URL: Issues, https://github.com/Bekichemeda/wikiscraper/issues
Classifier: Programming Language :: Python :: 3
Classifier: Operating System :: OS Independent
Requires-Python: >=3.9
License-File: License
Dynamic: license-file
